a7p/__init__.py
a7p/__main__.py
a7p/a7p.py
a7p/exceptions.py
a7p/factory.py
a7p/logger.py
a7p/profedit.proto.bak
a7p/profedit_pb2.py
a7p/profedit_pb2.pyi
a7p/spec_validator.py
a7p/yupy_schema.py
a7p/buf/__init__.py
a7p/buf/validate/__init__.py
a7p/buf/validate/expression_pb2.py
a7p/buf/validate/validate_pb2.py
a7p/buf/validate/priv/__init__.py
a7p/buf/validate/priv/private_pb2.py
a7p/protovalidate/__init__.py
a7p/protovalidate/validator.py
a7p/protovalidate/internal/__init__.py
a7p/protovalidate/internal/constraints.py
a7p/protovalidate/internal/extra_func.py
a7p/protovalidate/internal/string_format.py
a7p/pydantic/__init__.py
a7p/pydantic/correction.py
a7p/pydantic/models.py
a7p/pydantic/restore_tool.py
a7p/pydantic/template.py
a7p/pydantic/validate.py
a7p/recover/__init__.py
a7p/recover/recover.py
a7p/recover/recover_process.py
a7p/utils/__init__.py
a7p/utils/renamer.py
a7p-1.0.2.dist-info/licenses/LICENSE
a7p-1.0.2.dist-info/METADATA
a7p-1.0.2.dist-info/WHEEL
a7p-1.0.2.dist-info/entry_points.txt
a7p-1.0.2.dist-info/top_level.txt
a7p-1.0.2.dist-info/RECORD
