Metadata-Version: 2.4
Name: a7p
Version: 1.0.2
Summary: Simple python3 wrapper for .a7p files
Author: o-murphy
License:                     GNU GENERAL PUBLIC LICENSE
Project-URL: Homepage, https://github.com/o-murphy/a7p
Project-URL: Bug Reports, https://github.com/o-murphy/a7p/issues
Project-URL: Source, https://github.com/o-murphy/a7p
Keywords: protobuf,archer,a7p
Classifier: Intended Audience :: Developers
Classifier: Natural Language :: English
Classifier: Programming Language :: Python
Classifier: Topic :: Software Development :: Libraries :: Python Modules
Classifier: Programming Language :: Python :: 3
Classifier: Programming Language :: Python :: 3 :: Only
Classifier: Programming Language :: Python :: 3.10
Classifier: Programming Language :: Python :: 3.11
Classifier: Programming Language :: Python :: 3.12
Classifier: Programming Language :: Python :: 3.13
Classifier: Programming Language :: Python :: Implementation :: CPython
Requires-Python: >=3.10
License-File: LICENSE
Requires-Dist: google==3.0.0
Requires-Dist: protobuf==6.33.2
Requires-Dist: cel-python==0.4.0
Requires-Dist: tqdm==4.67.1
Requires-Dist: typing_extensions==4.15.0
Requires-Dist: yupy>=0.2.0b3
Provides-Extra: pydantic
Requires-Dist: pydantic==2.12.5; extra == "pydantic"
Provides-Extra: orjson
Requires-Dist: orjson==3.11.5; extra == "orjson"
Dynamic: license-file
